rede/__init__.py
rede/exceptions.py
rede/eefi/__init__.py
rede/eefi/models/AjustesCredito.py
rede/eefi/models/AjustesDebito.py
rede/eefi/models/AjustesDebitoEcommerce.py
rede/eefi/models/AjustesNet.py
rede/eefi/models/AjustesNetEcommerce.py
rede/eefi/models/Antecipacoes.py
rede/eefi/models/Avs.py
rede/eefi/models/Creditos.py
rede/eefi/models/DebitosLiquidados.py
rede/eefi/models/DebitosLiquidadosEcommerce.py
rede/eefi/models/DebitosPendentes.py
rede/eefi/models/DebitosPendentesEcommerce.py
rede/eefi/models/DesagendamentoParcelas.py
rede/eefi/models/DesagendamentoParcelasEcommerce.py
rede/eefi/models/Header.py
rede/eefi/models/HeaderMatriz.py
rede/eefi/models/SecureCode.py
rede/eefi/models/Serasa.py
rede/eefi/models/TotalizadorCreditos.py
rede/eefi/models/TotalizadorMatriz.py
rede/eefi/models/TrailerArquivo.py
rede/eefi/models/__init__.py
rede/eevc/__init__.py
rede/eevc/models/Header.py
rede/eevc/models/HeaderMatriz.py
rede/eevc/models/RegistroAVS.py
rede/eevc/models/RegistroAjustesCredito.py
rede/eevc/models/RegistroCVNSUDolar.py
rede/eevc/models/RegistroCVNSUParceladoIata.py
rede/eevc/models/RegistroCVNSUParceladoIataEcommerce.py
rede/eevc/models/RegistroCVNSUParceladoSemJuros.py
rede/eevc/models/RegistroCVNSUParceladoSemJurosEcommerce.py
rede/eevc/models/RegistroCVNSURecarga.py
rede/eevc/models/RegistroCVNSURotativo.py
rede/eevc/models/RegistroCVNSURotativoEcommerce.py
rede/eevc/models/RegistroParceladoIata.py
rede/eevc/models/RegistroParceladoSemJuros.py
rede/eevc/models/RegistroRVDolar.py
rede/eevc/models/RegistroRVIata.py
rede/eevc/models/RegistroRVParceladoSemJuros.py
rede/eevc/models/RegistroRVRotativo.py
rede/eevc/models/RegistroRequest.py
rede/eevc/models/RegistroRequestEcommerce.py
rede/eevc/models/RegistroSecureCode.py
rede/eevc/models/RegistroSerasa.py
rede/eevc/models/RegistroTotalizadorMatriz.py
rede/eevc/models/RegistroTrailerArquivo.py
rede/eevc/models/__init__.py
rede/eevd/__init__.py
rede/eevd/models/AdjustmentsNet.py
rede_edi-0.0.4.dist-info/LICENSE
rede_edi-0.0.4.dist-info/METADATA
rede_edi-0.0.4.dist-info/WHEEL
rede_edi-0.0.4.dist-info/top_level.txt
rede_edi-0.0.4.dist-info/RECORD
